kultimate/__init__.py
kultimate/app.css
kultimate/app.py
kultimate/screens/__init__.py
kultimate/screens/addTask.py
kultimate/screens/create_file.py
kultimate/screens/deleteTask.py
kultimate/screens/edit_task.py
kultimate/screens/selectFile.py
kultimate/utils/__init__.py
kultimate/utils/app_config.py
kultimate/utils/create_file.py
kultimate/utils/html_to_markdown.py
kultimate/utils/important_task.py
kultimate/utils/parser_html.py
kultimate/utils/process_yaml.py
kultimate/utils/prueba.py
kultimate/widgets/__init__.py
kultimate/widgets/directory.py
kultimate/widgets/stages.py
kultimate/widgets/stagesContainer.py
kultimate/widgets/task.py
kultimate-0.2.14.dist-info/METADATA
kultimate-0.2.14.dist-info/WHEEL
kultimate-0.2.14.dist-info/entry_points.txt
kultimate-0.2.14.dist-info/RECORD
