Metadata-Version: 2.1
Name: kultimate
Version: 0.2.14
Summary: Aplicación para manejar tableros kanban con markdown desde la línea de comandos
Author: Felipe
Author-email: 104157442+justafewwords4@users.noreply.github.com
Requires-Python: >=3.10,<4.0
Classifier: Programming Language :: Python :: 3
Classifier: Programming Language :: Python :: 3.10
Classifier: Programming Language :: Python :: 3.11
Requires-Dist: beautifulsoup4 (>=4.12.2,<5.0.0)
Requires-Dist: html2text (>=2020.1.16,<2021.0.0)
Requires-Dist: markdown (>=3.4.3,<4.0.0)
Requires-Dist: pyperclip (>=1.8.2,<2.0.0)
Requires-Dist: pyyaml (>=6.0,<7.0)
Requires-Dist: textual[dev] (>=0.27.0,<0.28.0)
Requires-Dist: typer[all] (>=0.9.0,<0.10.0)
